{"cameraMode":{"drawMode":0,"name":"Shaded","section":"Shading Mode"},"sceneLighting":false,"audioPlay":false,"sceneViewState":{"showFog":true,"showMaterialUpdate":false,"showSkybox":false,"showFlares":true,"showImageEffects":true,"showParticleSystems":true},"in2DMode":false,"pivot":{"x":-0.03899979591369629,"y":0.1343231201171875,"z":-0.07396507263183594},"rotation":{"x":-0.2625472843647003,"y":0.17594270408153535,"z":-0.04874638840556145,"w":-0.9475054740905762},"size":2.4131064414978029,"orthographic":false}